lastmileai/__init__.py
lastmileai-0.0.3.dist-info/LICENSE
lastmileai-0.0.3.dist-info/METADATA
lastmileai-0.0.3.dist-info/WHEEL
lastmileai-0.0.3.dist-info/top_level.txt
lastmileai-0.0.3.dist-info/RECORD
