Metadata-Version: 2.1
Name: lastmileai
Version: 0.0.3
Summary: Python library for LastMile AI API
Author-email: Suyog Sonwalkar <flux159@gmail.com>
Project-URL: Homepage, https://github.com/lastmile-ai/lastmileai-python
Project-URL: Bug Tracker, https://github.com/lastmile-ai/lastmileai-python/issues
Classifier: Intended Audience :: Developers
Classifier: Programming Language :: Python :: 3
Requires-Python: >=3.7
License-File: LICENSE
Requires-Dist: requests ==2.30.0
